discovery_imaging_utils/__init__.py
discovery_imaging_utils/denoise_ts_dict.py
discovery_imaging_utils/dense_ts_dictionary.py
discovery_imaging_utils/dictionary_utils.py
discovery_imaging_utils/func_denoising.py
discovery_imaging_utils/image_data_dictionary.py
discovery_imaging_utils/imaging_utils.py
discovery_imaging_utils/imaging_visualizations.py
discovery_imaging_utils/nifti_utils.py
discovery_imaging_utils/parc_ts_dictionary.py
discovery_imaging_utils/stats_utils.py
discovery_imaging_utils/triple_network_model.py
discovery_imaging_utils-0.1.4.1.dist-info/LICENSE.txt
discovery_imaging_utils-0.1.4.1.dist-info/METADATA
discovery_imaging_utils-0.1.4.1.dist-info/WHEEL
discovery_imaging_utils-0.1.4.1.dist-info/top_level.txt
discovery_imaging_utils-0.1.4.1.dist-info/RECORD
