Metadata-Version: 2.1
Name: discovery-imaging-utils
Version: 0.1.4.1
Summary: A package to aid in resting-state fMRI analysis
Home-page: https://github.com/erikglee/discovery_imaging_utils
Author: Erik Lee
Author-email: leex6144@umn.edu
License: UNKNOWN
Download-URL: https://github.com/erikglee/discovery_imaging_utils/archive/v0.1.4.tar.gz
Platform: UNKNOWN
Classifier: Programming Language :: Python :: 3
Classifier: License :: OSI Approved :: MIT License
Classifier: Operating System :: OS Independent
Requires-Python: >=3.6
